{"hash":"1c6819950e29e11d0c61e1eb07ca591ebb10be8e","data":{"project":{"title":"Samyak : A real-estate client website","date":"March 25, 2022","content":"<h1 id=\"real-estate-website-built-with-vuejs--tailwind-css\"><a href=\"#real-estate-website-built-with-vuejs--tailwind-css\" aria-hidden=\"true\"><span class=\"icon icon-link heading-anchor\"></span></a>Real-estate website built with Vue.js &#x26; Tailwind CSS</h1>\n<p>Recently I built a project for a client which consist of a basic website for a real-estate project. Here is the sneak-peak into the project and more is coming soon.</p>\n<h2 id=\"project-setup\"><a href=\"#project-setup\" aria-hidden=\"true\"><span class=\"icon icon-link heading-anchor\"></span></a>Project setup</h2>\n<div class=\"gridsome-highlight\" data-language=\"text\"><pre class=\"language-text\"><code class=\"language-text\">yarn install</code></pre></div>\n<h3 id=\"compiles-and-hot-reloads-for-development\"><a href=\"#compiles-and-hot-reloads-for-development\" aria-hidden=\"true\"><span class=\"icon icon-link heading-anchor\"></span></a>Compiles and hot-reloads for development</h3>\n<div class=\"gridsome-highlight\" data-language=\"text\"><pre class=\"language-text\"><code class=\"language-text\">yarn serve</code></pre></div>\n<h3 id=\"compiles-and-minifies-for-production\"><a href=\"#compiles-and-minifies-for-production\" aria-hidden=\"true\"><span class=\"icon icon-link heading-anchor\"></span></a>Compiles and minifies for production</h3>\n<div class=\"gridsome-highlight\" data-language=\"text\"><pre class=\"language-text\"><code class=\"language-text\">yarn build</code></pre></div>\n<h3 id=\"lints-and-fixes-files\"><a href=\"#lints-and-fixes-files\" aria-hidden=\"true\"><span class=\"icon icon-link heading-anchor\"></span></a>Lints and fixes files</h3>\n<div class=\"gridsome-highlight\" data-language=\"text\"><pre class=\"language-text\"><code class=\"language-text\">yarn lint</code></pre></div>\n<h3 id=\"customize-configuration\"><a href=\"#customize-configuration\" aria-hidden=\"true\"><span class=\"icon icon-link heading-anchor\"></span></a>Customize configuration</h3>\n<p>See <a href=\"https://cli.vuejs.org/config/\" target=\"_blank\" rel=\"noopener\">Configuration Reference</a>.</p>\n","category":"Vue3 | Web","summary":"A real-estate website designed by me for a client. Hosted on Render.com","gitlink":"https://github.com/sahilpatel09/real-estate","liveurl":"https://real-estate-jiaw.onrender.com/","tags":[{"title":"Vue3"},{"title":"Tailwindcss"}],"img":"https://github.com/sahilpatel09/real-estate/blob/main/public/screely-1654527222406.png?raw=true"}},"context":{}}