{"hash":"e9685ad4db68b5f74a190b0aaf06f1c649eac2fb","data":{"post":{"title":"How is Jamstack emerging!","date":"January 24, 2022","image":"https://d33wubrfki0l68.cloudfront.net/5a005724c095aebad3d85d9ead180a47fbfd1268/a8c43/img/cms/graphcms-jamstack.png","content":"<h2 id=\"hello-world\"><a href=\"#hello-world\" aria-hidden=\"true\"><span class=\"icon icon-link heading-anchor\"></span></a>Hello world!</h2>\n<p>This is where your content goes</p>\n<p>You can add <strong>markdown</strong> here</p>\n","tags":[{"title":"Blog","path":"/tag/Blog/"}]}},"context":{}}